<?xml version="1.0" encoding="UTF-8"?>
<objects serializationModel="Studio.02.03.00">
	<object class="AudioFile" id="{ad074b99-aa5f-4967-a944-a075c5ef8cd8}">
		<property name="assetPath">
			<value>grassClick3.wav</value>
		</property>
		<property name="frequencyInKHz">
			<value>44.0999985</value>
		</property>
		<property name="channelCount">
			<value>2</value>
		</property>
		<property name="length">
			<value>0.49519274376417233</value>
		</property>
		<relationship name="masterAssetFolder">
			<destination>{8115ddfe-677b-4b13-a87d-04e7c448f11e}</destination>
		</relationship>
	</object>
</objects>
